half_add_sub.v
module half_adder (
    input  wire a, b,     // Inputs
    output wire sum,      // Sum output
    output wire carry     // Carry output
);

    // Logic equations
    assign sum   = a ^ b;   // XOR for sum
    assign carry = a & b;   // AND for carry

endmodule

wave.vcd
$date
	Sat Nov 22 22:58:04 2025
$end
$version
	ModelSim Version 10.6c
$end
$timescale
	1ps
$end
$scope module half_adder $end
$var wire 1 ! b $end
$upscope $end
$enddefinitions $end
#0
1!
#100
0!
#200
1!
#300
0!
#400
1!
#500
0!
#600
1!
#700
0!
#800
1!
#900
0!
#1000
1!
#1100
0!
#1200
1!
#1300
0!
#1400
1!
#1500
0!
#1600
1!
#1700
0!
#1800
1!
#1900
0!
#2000
1!
#2100
0!
#2200
1!
#2300
0!
#2400
1!
#2500
0!
#2600
1!
#2700
0!
#2800
1!
