half_subtractor.v
module half_subtractor (
    input  wire a, b,         // Inputs
    output wire diff, borrow  // Outputs
);

    // Logic equations
    assign diff   = a ^ b;     // XOR for difference
    assign borrow = ~a & b;    // Borrow when a < b

endmodule

wave.sub.vcd
$date
	Sat Nov 22 23:18:24 2025
$end
$version
	ModelSim Version 10.6c
$end
$timescale
	1ps
$end
$scope module half_subtractor $end
$var wire 1 ! b $end
$upscope $end
$enddefinitions $end
#0
1!
#100
0!
#200
1!
#300
0!
#400
1!
#500
0!
#600
1!
#700
0!
#800
1!
#900
0!
#1000
1!
#1100
0!
#1200
1!
#1300
0!
#1400
1!
#1500
0!
#1600
1!
#1700
0!
#1800
1!
#1900
0!
#2000
1!
#2100
0!
#2200
1!
#2300
0!
#2400
1!
#2500
0!
#2600
1!
#2700
0!
#2800
1!
#2900
0!
#3000
1!
#3100
0!
#3200
1!
#3300
0!
#3400
1!
#3500
0!
#3600
1!
#3700
0!
#3800
1!
#3900
0!
#4000
1!
#4100
0!
#4200
1!
#4300
0!
#4400
1!
#4500
0!
#4600
1!
#4700
0!
